coolkit_client/__init__.py
coolkit_client/const.py
coolkit_client/device_control.py
coolkit_client/devices_repository.py
coolkit_client/discover.py
coolkit_client/log.py
coolkit_client/session.py
coolkit_client/device/__init__.py
coolkit_client/device/device.py
coolkit_client/device/switch.py
coolkit_client_phoenix-1.0.2.dist-info/LICENSE
coolkit_client_phoenix-1.0.2.dist-info/METADATA
coolkit_client_phoenix-1.0.2.dist-info/WHEEL
coolkit_client_phoenix-1.0.2.dist-info/top_level.txt
coolkit_client_phoenix-1.0.2.dist-info/RECORD
