Metadata-Version: 2.1
Name: coolkit-client-phoenix
Version: 1.0.2
Summary: Sonoff control library through coolkit/ewelink cloud
Home-page: https://github.com/phoenix128/python-coolkit-client
Author: Riccardo Tempesta
Author-email: info@riccardotempesta.com
License: UNKNOWN
Platform: UNKNOWN
Classifier: Programming Language :: Python :: 3.7
Classifier: License :: OSI Approved :: MIT License
Classifier: Operating System :: OS Independent
